{"name":"Tâm Cuồng","folder":"tamcuong","tacGia":"Sơ Hoà","theLoai":"Ngôn Tình","trangThai":"Đang ra","description":"Văn án:<br><br>Minh Thứ kết thúc một năm huấn luyện ở đội hành động đặc biệt, trở về Cục cảnh sát Hình sự thành phố Đông Nghiệp, thì cấp trên đã đổi người.<br><br>Mọi người: Anh Minh ơi, sếp mới nhìn nguy hiểm quá, hết dựa dẫm được rồi, anh coi chừng ổng \"đì\" anh á!<br><br>Minh Thứ:...... Tên đó \"đì\" tôi lâu rồi, tại mọi người không biết đó thôi.<br><br>Thành phố Đông Nghiệp phồn hoa, từ khi Minh Thứ trở về, bỗng án mạng không ngừng: người đàn ông thất nghiệp điên cuồng giết chóc tại quán cà phê, tai nạn thảm khốc ở công viên trò chơi bị bỏ hoang và những xác người chết bị chôn vùi....<br><br>Tổ trưởng Tổ trọng Án thành phố Đông Nghiệp Minh Thứ và Phó cục trưởng cục điều tra hình sự Tiêu Ngộ An cùng nhau hợp sức giải quyết vụ án"}