{"name":"Nương Tử Mau Tới Bảo Vệ Ta","folder":"nuongtumautoibaoveta","tacGia":"Ngọc Tịnh Cam Lộ","theLoai":"Ngôn Tình","trangThai":"Đang ra","description":"VĂN&nbsp;ÁN<br><br>Trong cuộc đời của Lý Dụ, trừ thích nhất thời thời khắc khắc dính lấy nương tử nhà mình, hưởng thụ sự bảo vệ của nương tử, nhà có nương tử lợi hại, hắn rất kiêu ngạo đó! Nếu ai không phục, thử không phục xem!<br><br>Tô Nhược Tuyết sống lại một lần nữa, nhưng ngoài ý muốn cuộc sống của nàng lại bị Lý nhị thiếu quấn chặt lấy, từ nay về sau, cả đời bình lặng như nước của nàng loạn hết cả lên....<br><br>Nữ chính lạnh lùng thích động thủ không thích nói chuyện, nam chính yêu động thủ trước, còn nói chuyện thì.....<br><br>Tiểu kịch trường:<br><br>Gần đây Lý Dụ rất buồn.<br><br>Chỉ cần hắn làm loạn là tiểu nương tử nhà hắn liền sờ sờ nhuyễn roi tơ bạc bên hông không nói lời nào. Nhưng nhìn thấy dáng vẻ này của nàng, hắn lại càng muốn nổi loạn. Mọi người nói hắn đánh không lại, đánh không lại thế nào?<br><br>Đây là vấn đề lớn...<br><br>Truyện này song trùng sinh, có điều nữ chính và nam phụ trùng sinh, Lý nhị thiếu bày tỏ, nam phụ là vật gì, hừ!<br><br>Nhân vật chính: Tô Nhược Tuyết, Lý Dụ.<br><br>Nhân vật phụ: Người Tô gia, người Lý phủ<br><br>Cùng hệ liệt: Tướng quân sủng thê - &nbsp;Tô Nhược U và Bùi Hạo. Dã thú ngửi kiều hoa - Tô Nhược Nhị và Mẫn Hoàng Duệ."}